web_crawler/__init__.py
web_crawler/models/__init__.py
web_crawler/services/__init__.py
web_crawler/web_crawler.py
web_crawler_cli/__init__.py
web_crawler_cli/commands/__init__.py
web_crawler_cli/web_crawler_cli.py
py_webcrawler-0.1.0.dist-info/entry_points.txt
py_webcrawler-0.1.0.dist-info/LICENSE
py_webcrawler-0.1.0.dist-info/WHEEL
py_webcrawler-0.1.0.dist-info/METADATA
py_webcrawler-0.1.0.dist-info/RECORD
