Metadata-Version: 2.1
Name: py-webcrawler
Version: 0.1.0
Summary: python web crawler
Author: Patricio Tula
Author-email: tula.patricio@gmail.com
Requires-Python: >=3.9,<4.0
Classifier: Programming Language :: Python :: 3
Classifier: Programming Language :: Python :: 3.9
Requires-Dist: bs4 (>=0.0.1,<0.0.2)
Requires-Dist: requests (>=2.25.1,<3.0.0)
